{
  "accession": "S-EPMC5750525",
  "type": "study",
  "title": "Cerenkov-Activated Sticky Tag for In Vivo Fluorescence Imaging.",
  "author": "Das S Haedicke K Grimm J",
  "links": 4,
  "files": 1,
  "release_date": "2018-01-01",
  "views": 12,
  "isPublic": true,
  "content": "S-EPMC5750525 PMC5750525 Cerenkov-Activated Sticky Tag for In Vivo Fluorescence Imaging. A big challenge in the clinical use of Cerenkov luminescence (CL) imaging is its low signal intensity, which is several orders of magnitude below ambient light. Consequently, highly sensitive cameras"
}