{
  "accession": "S-BIAD1900",
  "type": "study",
  "title": "Systematic Benchmarking of High-Throughput Subcellular Spatial Transcriptomics Platforms",
  "author": "",
  "links": 0,
  "files": 36,
  "release_date": "2025-05-05",
  "views": 1,
  "isPublic": true,
  "content": "S-BIAD1900 Systematic Benchmarking of High-Throughput Subcellular Spatial Transcriptomics Platforms We benchmarked five advanced spatial transcriptomics (ST) platforms: Stereo-seq v1.3, Visium HD FF, Visium HD FFPE, CosMx 6K, and Xenium 5K. These platforms were selected for their high-throughput"
}